gatling/__init__.py
gatling/runtime/__init__.py
gatling/runtime/taskflow_manager.py
gatling/runtime/task_manager/__init__.py
gatling/runtime/task_manager/coroutine_executor.py
gatling/runtime/task_manager/runtime_task_manager_base.py
gatling/runtime/task_manager/runtime_task_manager_coroutine_function.py
gatling/runtime/task_manager/runtime_task_manager_coroutine_iterator.py
gatling/runtime/task_manager/runtime_task_manager_process_function.py
gatling/runtime/task_manager/runtime_task_manager_process_iterator.py
gatling/runtime/task_manager/runtime_task_manager_processing_function.py
gatling/runtime/task_manager/runtime_task_manager_processing_iterator.py
gatling/runtime/task_manager/runtime_task_manager_thread_function.py
gatling/runtime/task_manager/runtime_task_manager_thread_iterator.py
gatling/storage/__init__.py
gatling/storage/g_dctn/__init__.py
gatling/storage/g_dctn/base_dctn.py
gatling/storage/g_dctn/memory_dctn.py
gatling/storage/g_queue/__init__.py
gatling/storage/g_queue/base_queue.py
gatling/storage/g_queue/memory_queue.py
gatling/storage/g_set/__init__.py
gatling/storage/g_sfs/__init__.py
gatling/storage/g_sfs/sfs_helper.py
gatling/storage/g_sfs/sfs_main.py
gatling/storage/g_table/__init__.py
gatling/storage/g_table/a_const_debug.py
gatling/storage/g_table/base_table_ao.py
gatling/storage/g_table/table_ao_file_tsv.py
gatling/storage/g_table/help_tools/__init__.py
gatling/storage/g_table/help_tools/file_tools.py
gatling/storage/g_table/help_tools/sent_tools.py
gatling/storage/g_table/help_tools/slice_tools.py
gatling/utility/__init__.py
gatling/utility/decorator_tools.py
gatling/utility/error_tools.py
gatling/utility/help_fctns.py
gatling/utility/http_fetch_fctns.py
gatling/utility/io_fctns.py
gatling/utility/mem_tools.py
gatling/utility/profile_tools.py
gatling/utility/proxy_mana.py
gatling/utility/rand_tools.py
gatling/utility/watch.py
gatling/utility/xprint.py
gatling/utility/xstr.py
gatling/vtasks/__init__.py
gatling/vtasks/a_const.py
gatling-0.3.0.25.3.dist-info/METADATA
gatling-0.3.0.25.3.dist-info/WHEEL
gatling-0.3.0.25.3.dist-info/top_level.txt
gatling-0.3.0.25.3.dist-info/RECORD
