Metadata-Version: 2.4
Name: gatling
Version: 0.3.0.25.3
Summary: A unified I/O management toolkit supporting threads, coroutines, files, databases, and data formats
Author-email: MacroMozilla <honyzeng7@gmail.com>
License: MIT
Project-URL: Homepage, https://github.com/MacroMozilla/gatling
Project-URL: Repository, https://github.com/MacroMozilla/gatling
Requires-Python: >=3.11
Requires-Dist: aiohappyeyeballs==2.6.1
Requires-Dist: aiohttp==3.13.2
Requires-Dist: aiosignal==1.4.0
Requires-Dist: asttokens==3.0.1
Requires-Dist: asyncio==4.0.0
Requires-Dist: attrs==25.4.0
Requires-Dist: ciso8601==2.3.3
Requires-Dist: colorama==0.4.6
Requires-Dist: dill==0.4.0
Requires-Dist: executing==2.2.1
Requires-Dist: Faker==38.2.0
Requires-Dist: frozenlist==1.8.0
Requires-Dist: icecream==2.1.8
Requires-Dist: idna==3.11
Requires-Dist: line_profiler==5.0.0
Requires-Dist: multidict==6.7.0
Requires-Dist: multiprocess==0.70.18
Requires-Dist: orjson==3.11.4
Requires-Dist: packaging==25.0
Requires-Dist: pipdeptree==2.28.0
Requires-Dist: propcache==0.4.1
Requires-Dist: psutil==7.1.3
Requires-Dist: Pygments==2.19.2
Requires-Dist: tqdm==4.67.1
Requires-Dist: typing_extensions==4.15.0
Requires-Dist: tzdata==2025.2
Requires-Dist: yarl==1.22.0
Requires-Dist: zstandard==0.25.0
